routio/__init__.py
routio/__main__.py
routio/array.py
routio/camera.py
routio/ignition.py
routio/pyroutio.so
routio/tornado.py
routio/messages/__init__.py
routio/messages/__main__.py
routio/messages/cli.py
routio/messages/syntax.py
routio/messages/library/__init__.py
routio/messages/library/geometry.msg
routio/messages/templates/__init__.py
routio/messages/templates/cpp.tpl
routio/messages/templates/python.tpl
routio/source/__init__.py
routio/source/algorithms.h
routio/source/array.cpp
routio/source/client.cpp
routio/source/datatypes.cpp
routio/source/debug.cpp
routio/source/debug.h
routio/source/loop.cpp
routio/source/message.cpp
routio/source/routing.cpp
routio/source/server.cpp
routio/source/wrapper.cpp
routio/source/routio/__init__.py
routio/source/routio/array.h
routio/source/routio/camera.h
routio/source/routio/client.h
routio/source/routio/datatypes.h
routio/source/routio/helpers.h
routio/source/routio/loop.h
routio/source/routio/message.h
routio/source/routio/routing.h
routio/source/routio/server.h
routio-1.0.0.dist-info/METADATA
routio-1.0.0.dist-info/WHEEL
routio-1.0.0.dist-info/entry_points.txt
routio-1.0.0.dist-info/top_level.txt
routio-1.0.0.dist-info/RECORD
