Metadata-Version: 2.1
Name: routio
Version: 1.0.0
Summary: Python package for routio IPC library
Home-page: https://github.com/lukacu/routio
Author: Luka Cehovin Zajc
Author-email: luka.cehovin@protonmail.com
License: UNKNOWN
Project-URL: Documentation, https://github.com/lukacu/routio
Project-URL: Source Code, https://github.com/lukacu/routio
Project-URL: Bug Tracker, https://github.com/lukacu/routio/issues
Keywords: ipc,interprocess,communication,messaging,rpc
Platform: UNKNOWN
Classifier: Development Status :: 4 - Beta
Classifier: Intended Audience :: Developers
Classifier: Operating System :: POSIX :: Linux
Classifier: Programming Language :: C++
Classifier: Programming Language :: Python
Classifier: Programming Language :: Python :: 3
Classifier: Programming Language :: Python :: 3.10
Classifier: Programming Language :: Python :: 3.11
Classifier: Programming Language :: Python :: 3.12
Classifier: Programming Language :: Python :: 3.13
Classifier: Topic :: Software Development :: Libraries
Classifier: Topic :: System :: Distributed Computing
Requires-Python: >=3.10
